{"appleSKU":"","appleTeamID":"","enableCodelessAutoInitialization":false,"enableUnityGamingServicesAutoInitialization":true,"products":[{"id":"com.dany.city.coins500","type":0,"storeIDs":[],"defaultDescription":{"googleLocale":4,"title":"","description":""},"screenshotPath":"","applePriceTier":0,"googlePrice":{"data":[0,0,0,0],"num":0.0},"pricingTemplateID":"","descriptions":[],"udpPrice":{"data":[0,0,0,0],"num":0.0},"payouts":[]},{"id":"com.dany.city.coins1000","type":0,"storeIDs":[],"defaultDescription":{"googleLocale":4,"title":"","description":""},"screenshotPath":"","applePriceTier":0,"googlePrice":{"data":[0,0,0,0],"num":0.0},"pricingTemplateID":"","descriptions":[],"udpPrice":{"data":[0,0,0,0],"num":0.0},"payouts":[]},{"id":"com.dany.city.redcar","type":1,"storeIDs":[],"defaultDescription":{"googleLocale":4,"title":"","description":""},"screenshotPath":"","applePriceTier":0,"googlePrice":{"data":[0,0,0,0],"num":0.0},"pricingTemplateID":"","descriptions":[],"udpPrice":{"data":[0,0,0,0],"num":0.0},"payouts":[]},{"id":"com.dany.city.greencar","type":1,"storeIDs":[],"defaultDescription":{"googleLocale":4,"title":"","description":""},"screenshotPath":"","applePriceTier":0,"googlePrice":{"data":[0,0,0,0],"num":0.0},"pricingTemplateID":"","descriptions":[],"udpPrice":{"data":[0,0,0,0],"num":0.0},"payouts":[]},{"id":"com.dany.city.removeads","type":0,"storeIDs":[],"defaultDescription":{"googleLocale":4,"title":"","description":""},"screenshotPath":"","applePriceTier":0,"googlePrice":{"data":[0,0,0,0],"num":0.0},"pricingTemplateID":"","descriptions":[],"udpPrice":{"data":[0,0,0,0],"num":0.0},"payouts":[]}]}